pyapimocker/__init__.py
pyapimocker/cli.py
pyapimocker/models.py
pyapimocker/server.py
pyapimocker-0.1.0.dist-info/METADATA
pyapimocker-0.1.0.dist-info/WHEEL
pyapimocker-0.1.0.dist-info/entry_points.txt
pyapimocker-0.1.0.dist-info/licenses/LICENSE
pyapimocker-0.1.0.dist-info/RECORD
