Metadata-Version: 2.4
Name: pyapimocker
Version: 0.1.0
Summary: A lightweight, config-driven mock API server for Python teams
Project-URL: Homepage, https://github.com/shreyasbhaskar/pyapimocker
Project-URL: Documentation, https://github.com/shreyasbhaskar/pyapimocker#readme
Project-URL: Repository, https://github.com/shreyasbhaskar/pyapimocker.git
Project-URL: Issues, https://github.com/shreyasbhaskar/pyapimocker/issues
Author-email: Shreyas Bhaskar <shreyasbhaskar@gmail.com>
License-Expression: MIT
License-File: LICENSE
Classifier: Development Status :: 4 - Beta
Classifier: Intended Audience :: Developers
Classifier: License :: OSI Approved :: MIT License
Classifier: Programming Language :: Python :: 3
Classifier: Programming Language :: Python :: 3.8
Classifier: Programming Language :: Python :: 3.9
Classifier: Programming Language :: Python :: 3.10
Classifier: Programming Language :: Python :: 3.11
Classifier: Topic :: Software Development :: Libraries :: Python Modules
Classifier: Topic :: Software Development :: Testing
Requires-Python: >=3.8
Requires-Dist: faker>=19.0.0
Requires-Dist: fastapi>=0.68.0
Requires-Dist: httpx>=0.24.0
Requires-Dist: jinja2>=3.0.0
Requires-Dist: pydantic>=2.0.0
Requires-Dist: pyyaml>=6.0
Requires-Dist: uvicorn>=0.15.0
Provides-Extra: dev
Requires-Dist: black>=22.0.0; extra == 'dev'
Requires-Dist: isort>=5.0.0; extra == 'dev'
Requires-Dist: mypy>=0.900; extra == 'dev'
Requires-Dist: pytest-asyncio>=0.18.0; extra == 'dev'
Requires-Dist: pytest>=7.0.0; extra == 'dev'
